README.rst
coloredlogger.py
setup.py
coloredlogger.egg-info/PKG-INFO
coloredlogger.egg-info/SOURCES.txt
coloredlogger.egg-info/dependency_links.txt
coloredlogger.egg-info/requires.txt
coloredlogger.egg-info/top_level.txt