Metadata-Version: 1.1
Name: coloredlogger
Version: 1.3.12
Summary: Colored Logger for Python
Home-page: https://github.com/fmakdemir/colored-logger
Author: Fma
Author-email: fmakdemir@gmail.com
License: MIT
Keywords: coloredlogger logger log colored linux color colour coloured
Platform: UNKNOWN
Classifier: Development Status :: 4 - Beta
Classifier: Intended Audience :: Developers
Classifier: Topic :: System :: Logging
Classifier: License :: OSI Approved :: MIT License
Classifier: Programming Language :: Python :: 3
Classifier: Programming Language :: Python :: 3.3
Classifier: Programming Language :: Python :: 3.4
Classifier: Programming Language :: Python :: 3.5
Classifier: Programming Language :: Python :: 3.6
